gempy_plugins/__init__.py
gempy_plugins/_version.py
gempy_plugins/optional_dependencies.py
gempy_plugins/gdal_topography/__init__.py
gempy_plugins/gdal_topography/gdal_reader.py
gempy_plugins/gdal_topography/load_dem_gdal.py
gempy_plugins/gdal_topography/tests/__init__.py
gempy_plugins/gdal_topography/tests/test_gdal.py
gempy_plugins/kriging/__init__.py
gempy_plugins/kriging/coKriging.py
gempy_plugins/kriging/kriging.py
gempy_plugins/map2gempy/__init__.py
gempy_plugins/map2gempy/map2gempy.py
gempy_plugins/map2gempy/tests/__init__.py
gempy_plugins/map2gempy/tests/test_map2loop.py
gempy_plugins/orientations_generator/__init__.py
gempy_plugins/orientations_generator/_orientations_generator.py
gempy_plugins/orientations_generator/tests/__init__.py
gempy_plugins/orientations_generator/tests/test_orientations_from_surface_points.py
gempy_plugins/spill_analysis/__init__.py
gempy_plugins/spill_analysis/spill_analysis.py
gempy_plugins/topology_analysis/__init__.py
gempy_plugins/topology_analysis/topology.py
gempy_plugins/utils/__init__.py
gempy_plugins/utils/analysis.py
gempy_plugins/utils/export.py
gempy_plugins/utils/gradient.py
gempy_plugins/utils/input_manipulation.py
tests/__init__.py
tests/test_addons/__init__.py
tests/test_integrations/__init__.py
gempy_plugins-2024.1.0.dist-info/AUTHORS.rst
gempy_plugins-2024.1.0.dist-info/LICENSE
gempy_plugins-2024.1.0.dist-info/METADATA
gempy_plugins-2024.1.0.dist-info/WHEEL
gempy_plugins-2024.1.0.dist-info/top_level.txt
gempy_plugins-2024.1.0.dist-info/RECORD
