Metadata-Version: 2.1
Name: gempy_plugins
Version: 2024.1.0
Summary: Extra plugins for the geological modeling package GemPy
Home-page: 
Author: Miguel de la Varga
Author-email: miguel@terranigma-solutions.com
License: EUPL-1.2
Classifier: Development Status :: 3 - Alpha
Classifier: Intended Audience :: Science/Research
Classifier: Topic :: Scientific/Engineering :: Visualization
Classifier: Topic :: Scientific/Engineering :: GIS
Classifier: Programming Language :: Python :: 3.10
Requires-Python: >=3.10
License-File: LICENSE
License-File: AUTHORS.rst
